csv2dictionary/__init__.py
csv2dictionary/csvpro.py
csv2dictionary-0.0.2.dist-info/LICENSE
csv2dictionary-0.0.2.dist-info/METADATA
csv2dictionary-0.0.2.dist-info/WHEEL
csv2dictionary-0.0.2.dist-info/top_level.txt
csv2dictionary-0.0.2.dist-info/RECORD
