Metadata-Version: 2.1
Name: csv2dictionary
Version: 0.0.2
Summary: converts csv to a dictionary
Home-page: https://github.com/colemalphrus/csv2dictionary
Author: Cole Malphrus
Author-email: cole@malphrus.tech
License: UNKNOWN
Platform: UNKNOWN
Classifier: Programming Language :: Python :: 3
Classifier: License :: OSI Approved :: MIT License
Classifier: Operating System :: OS Independent
Requires-Python: >=3.6
